fancy/trainer/LICENSE.txt
fancy/trainer/README.md
fancy/trainer/TODO.md
fancy/trainer/__init__.py
fancy/trainer/configs/__init__.py
fancy/trainer/configs/data_loader_collection_config.py
fancy/trainer/configs/dataset_config.py
fancy/trainer/configs/importer_config.py
fancy/trainer/configs/loss_function_config.py
fancy/trainer/configs/metrics_collection_config.py
fancy/trainer/configs/model_config.py
fancy/trainer/configs/optimizer_config.py
fancy/trainer/configs/processes.py
fancy/trainer/configs/trainer_config.py
fancy/trainer/configs/training_config.py
fancy/trainer/configs/transform_config.py
fancy/trainer/dataset/__init__.py
fancy/trainer/dataset/dataset.py
fancy/trainer/metrics/__init__.py
fancy/trainer/metrics/accuracy.py
fancy/trainer/metrics/loss.py
fancy/trainer/metrics/metric_base.py
fancy/trainer/metrics/rmse.py
fancy/trainer/model/__init__.py
fancy/trainer/model/checkpoint.py
fancy/trainer/model/checkpoint_plotter.py
fancy/trainer/model/checkpoint_plotter_base.py
fancy/trainer/model/tensor_proxy.py
fancy/trainer/scripts/__init__.py
fancy/trainer/scripts/train.py
fancy/trainer/tests/__init__.py
fancy/trainer/tests/unit/__init__.py
fancy/trainer/tests/unit/test_tensor_proxy.py
fancy/trainer/training/__init__.py
fancy/trainer/training/data_loader_collection.py
fancy/trainer/training/metrics_collection.py
fancy/trainer/training/trainer.py
fancy/trainer/transform_factories/__init__.py
fancy/trainer/transform_factories/transform_factory.py
fancy/trainer/transforms/__init__.py
fancy/trainer/transforms/convert_mode.py
fancy/trainer/transforms/normalize_both_input_and_target.py
fancy/trainer/transforms/target_handler.py
fancy_trainer-0.0.10.dist-info/METADATA
fancy_trainer-0.0.10.dist-info/WHEEL
fancy_trainer-0.0.10.dist-info/entry_points.txt
fancy_trainer-0.0.10.dist-info/top_level.txt
fancy_trainer-0.0.10.dist-info/RECORD
